ectoplasm/__init__.py
ectoplasm/__main__.py
ectoplasm/patches.py
ectoplasm/test-ectoplasm.py
ectoplasm_steganography-0.0.11.dist-info/METADATA
ectoplasm_steganography-0.0.11.dist-info/WHEEL
ectoplasm_steganography-0.0.11.dist-info/licenses/LICENSE
ectoplasm_steganography-0.0.11.dist-info/RECORD
