Metadata-Version: 2.4
Name: Ectoplasm-Steganography
Version: 0.0.11
Summary: A versatile lossless text/data encoding steganography algorithm + pipeline for images
Project-URL: Homepage, https://github.com/thomas-xin/Ectoplasm-Steganography
Project-URL: Issues, https://github.com/thomas-xin/Ectoplasm-Steganography/issues
Author-email: thomas-xin <thomasxin@gmail.com>
License-File: LICENSE
Classifier: License :: OSI Approved :: MIT License
Classifier: Operating System :: OS Independent
Classifier: Programming Language :: Python :: 3
Requires-Python: >=3.9
Requires-Dist: base45>=0.4.4
Requires-Dist: bitarray>=3.0.0
Requires-Dist: brotli>=1.1.0
Requires-Dist: numpy>=2.2.6
Requires-Dist: opencv-python>=4.10.0.84
Requires-Dist: pillow>=11.0.0
Requires-Dist: pyqrcode>=1.2.1
Requires-Dist: pyzbar>=0.1.9
Requires-Dist: raptorq>=2.0.0
Requires-Dist: reedsolo>=1.7.0
Provides-Extra: full
Requires-Dist: c2pa-python>=0.4.0; extra == 'full'
Requires-Dist: paq>=0.1.1; extra == 'full'
